cert_schema/__init__.py
cert_schema/__version__.py
cert_schema/context_urls.json
cert_schema/context_urls.py
cert_schema/digests.py
cert_schema/errors.py
cert_schema/jsonld_helpers.py
cert_schema/schema_validator.py
cert_schema/1.1/certificate-schema-v1-1.json
cert_schema/1.1/issuer-schema-v1-1.json
cert_schema/1.2/assertion-1.2.json
cert_schema/1.2/blockchain-certificate-1.2.json
cert_schema/1.2/blockchain-receipt-1.2.json
cert_schema/1.2/certificate-1.2.json
cert_schema/1.2/certificate-document-1.2.json
cert_schema/1.2/context.json
cert_schema/1.2/issuer-1.2.json
cert_schema/1.2/issuer-id-1.2.json
cert_schema/2.0/context.json
cert_schema/2.0/issuerSchema.json
cert_schema/2.0/merkleProof2017Schema.json
cert_schema/2.0/obi.json
cert_schema/2.0/recipientSchema.json
cert_schema/2.0/schema.json
cert_schema/2.0/signatureLineSchema.json
cert_schema/2.0-alpha/context.json
cert_schema/2.0-alpha/issuerSchema.json
cert_schema/2.0-alpha/merkleProof2017Schema.json
cert_schema/2.0-alpha/recipientSchema.json
cert_schema/2.0-alpha/schema.json
cert_schema/2.0-alpha/signatureLineSchema.json
cert_schema/2.1/context.json
cert_schema/2.1/issuerSchema.json
cert_schema/2.1/merkleProof2017Schema.json
cert_schema/2.1/obi.json
cert_schema/2.1/recipientSchema.json
cert_schema/2.1/schema.json
cert_schema/2.1/signatureLineSchema.json
cert_schema/3.0/claimSchema.json
cert_schema/3.0/context.json
cert_schema/3.0/credential.json
cert_schema/3.0/credentialSubjectSchema.json
cert_schema/3.0/displaySchema.json
cert_schema/3.0/merkleProof2019Context.json
cert_schema/3.0/merkleProof2019Schema.json
cert_schema/3.0/schema.json
cert_schema/3.0-alpha/context.json
cert_schema/3.0-alpha/credential.json
cert_schema/3.0-alpha/exampleCredential.json
cert_schema/3.0-alpha/issuerSchema.json
cert_schema/3.0-alpha/merkleProof2019Context.json
cert_schema/3.0-alpha/merkleProof2019Schema.json
cert_schema/3.0-alpha/schema.json
cert_schema/3.0-beta/context.json
cert_schema/3.0-beta/credential.json
cert_schema-3.10.0.dist-info/licenses/LICENSE
cert_schema-3.10.0.dist-info/METADATA
cert_schema-3.10.0.dist-info/WHEEL
cert_schema-3.10.0.dist-info/top_level.txt
cert_schema-3.10.0.dist-info/RECORD
