Metadata-Version: 2.4
Name: cert-schema
Version: 3.10.0
Summary: Blockchain certificates JSON-LD context and JSON schemas
Home-page: https://github.com/blockchain-certificates/cert-schema
Author: info@blockcerts.org
Author-email: info@blockcerts.org
License: MIT
License-File: LICENSE
Requires-Dist: pyld>=2.0.3
Requires-Dist: jsonschema>=2.6.0
Requires-Dist: tox>=3.0.0
Requires-Dist: validators>=0.12.1
Requires-Dist: setuptools>=75.8.0
Dynamic: author
Dynamic: author-email
Dynamic: description
Dynamic: description-content-type
Dynamic: home-page
Dynamic: license
Dynamic: license-file
Dynamic: requires-dist
Dynamic: summary
